setup.cfg
setup.py
pi2143oop/CanvasClass.py
pi2143oop/CircleClass.py
pi2143oop/DotClass.py
pi2143oop/ErrorClass.py
pi2143oop/LineClass.py
pi2143oop/RectangleClass.py
pi2143oop/RhombClass.py
pi2143oop/Settings.py
pi2143oop/SquareClass.py
pi2143oop/TriangleClass.py
pi2143oop/__init__.py
pi2143oop.egg-info/PKG-INFO
pi2143oop.egg-info/SOURCES.txt
pi2143oop.egg-info/dependency_links.txt
pi2143oop.egg-info/not-zip-safe
pi2143oop.egg-info/top_level.txt