Metadata-Version: 1.0
Name: pi2143oop
Version: 1.6
Summary: OOP tasks
Home-page: UNKNOWN
Author: UNKNOWN
Author-email: good-i-evil@yandex.ru
License: UNKNOWN
Platform: UNKNOWN
